poor_smime_sign/__init__.py
poor_smime_sign/poor_smime_sign.py
poor_smime_sign-2.0.3.dist-info/DESCRIPTION.rst
poor_smime_sign-2.0.3.dist-info/METADATA
poor_smime_sign-2.0.3.dist-info/RECORD
poor_smime_sign-2.0.3.dist-info/WHEEL
poor_smime_sign-2.0.3.dist-info/metadata.json
poor_smime_sign-2.0.3.dist-info/top_level.txt
