Metadata-Version: 2.0
Name: poor-smime-sign
Version: 2.0.3
Summary: A very poor tool to do S/MIME signatures on binary files. Probably insecurely.
Home-page: https://github.com/seporaitis/poor-smime-sign
Author: Julius Seporaitis
Author-email: julius@seporaitis.net
License: MIT
Keywords: smime sign passbook
Platform: UNKNOWN
Classifier: Development Status :: 3 - Alpha
Classifier: Intended Audience :: Developers
Classifier: License :: OSI Approved :: MIT License
Classifier: Natural Language :: English
Classifier: Programming Language :: Python :: 2
Classifier: Programming Language :: Python :: 2.7
Classifier: Programming Language :: Python :: 3
Classifier: Programming Language :: Python :: 3.3
Classifier: Programming Language :: Python :: 3.4
